jk_ff.v
module jk_ff (
 input preset, // Asynchronous reset (active high)
 input clk,
 input j,
 input k,
 output reg q,
 output qn
);
assign qn = ~q;
always @(posedge clk or posedge preset) begin
 if (preset)
 q <= 1'b1; // Reset
 else begin
 case ({j, k})
 2'b00: q <= q; // Hold
 2'b01: q <= 1'b0; // Reset

2'b10: q <= 1'b1; // Set
2'b11: q <= ~q; // Toggle
 endcase
 end
end
endmodule

jk_ff_tb.v
module jk_ff_tb;
 reg preset; // Asynchronous reset (active high)
 reg clk;
 reg j, k;
 wire q, qn;
 // DUT instantiation
 jk_ff dut (
 .preset(preset),
 .clk (clk),
 .j (j),
 .k (k),
 .q (q),
 .qn (qn)
 );
 // Clock generation: 10 ns period
 always #5 clk <= ~clk;
 // Monitor the input and output
 initial begin
	 $monitor("%0t|preset=%b j=%b k=%b|q=%b qn=%b",$time,preset,j,k,q,qn);
 end
 initial begin
 // Initial values
 clk = 0;
 preset = 1; // Assert async reset
 j = 0;
 k = 0;
 // Hold reset for a while
 #7; // NOT aligned with clock edge	
 preset = 0; // Deassert reset (async)
 // Apply JK combinations	
 #10 j = 0; k = 0; // Hold	
 #10 j = 0; k = 1; // Reset
 #10 j = 1; k = 0; // Set	
 #10 j = 1; k = 1; // Toggle		
 #10 j = 1; k = 1; // Toggle again			
 // Assert async reset in middle of clock cycle
 #3 preset = 1;
 #4 preset = 0;
 #20 $finish;
 end			
 // Dump waves
 initial begin				
 $dumpfile("jk_ff_async.vcd");
 $dumpvars(0, jk_ff_tb);
 end
endmodule

obj_dir/jk_ff_async.vcd
$version Generated by VerilatedVcd $end
$timescale 1ps $end

 $scope module TOP $end
  $scope module jk_ff_tb $end
   $var wire  1 $ clk $end
   $var wire  1 % j $end
   $var wire  1 & k $end
   $var wire  1 # preset $end
   $var wire  1 ' q $end
   $var wire  1 ( qn $end
   $scope module dut $end
    $var wire  1 $ clk $end
    $var wire  1 % j $end
    $var wire  1 & k $end
    $var wire  1 # preset $end
    $var wire  1 ' q $end
    $var wire  1 ( qn $end
   $upscope $end
  $upscope $end
 $upscope $end
$enddefinitions $end


#0
1#
0$
0%
0&
0'
1(
#5
1$
1'
0(
#7
0#
#10
0$
#15
1$
#17
#20
0$
#25
1$
#27
1&
#30
0$
#35
1$
0'
1(
#37
1%
0&
#40
0$
#45
1$
1'
0(
#47
1&
#50
0$
#55
1$
0'
1(
#57
#60
1#
0$
1'
0(
#64
0#
#65
1$
0'
1(
#70
0$
#75
1$
1'
0(
